cwl2ogc/__about__.py
cwl2ogc/__init__.py
cwl2ogc/cli.py
cwl2ogc/stac_collection.py
cwl2ogc/stac_item.py
cwl2ogc-0.10.0.dist-info/METADATA
cwl2ogc-0.10.0.dist-info/WHEEL
cwl2ogc-0.10.0.dist-info/entry_points.txt
cwl2ogc-0.10.0.dist-info/licenses/LICENSE
cwl2ogc-0.10.0.dist-info/RECORD
