Metadata-Version: 2.4
Name: cwl2ogc
Version: 0.10.0
Summary: CWL Worflow inputs/outputs to OGC API Processes inputs/outputs
Project-URL: Documentation, https://github.com/eoap/cwl2ogc#readme
Project-URL: Issues, https://github.com/eoap/cwl2ogc/issues
Project-URL: Source, https://github.com/eoap/cwl2ogc
Author-email: Fabrice Brito <info@terradue.com>, Simone Tripodi <info@terradue.com>
License-Expression: MIT
License-File: LICENSE
Classifier: Development Status :: 4 - Beta
Classifier: Programming Language :: Python
Classifier: Programming Language :: Python :: 3.8
Classifier: Programming Language :: Python :: 3.9
Classifier: Programming Language :: Python :: 3.10
Classifier: Programming Language :: Python :: 3.11
Classifier: Programming Language :: Python :: 3.12
Classifier: Programming Language :: Python :: Implementation :: CPython
Classifier: Programming Language :: Python :: Implementation :: PyPy
Requires-Python: >=3.8
Requires-Dist: click
Requires-Dist: cwl-utils>=0.40
Requires-Dist: loguru
Requires-Dist: pyyaml
